video2sub/__init__.py
video2sub/utils.py
video2sub/video2sub.py
video2sub-0.1.1.dist-info/LICENSE
video2sub-0.1.1.dist-info/METADATA
video2sub-0.1.1.dist-info/WHEEL
video2sub-0.1.1.dist-info/entry_points.txt
video2sub-0.1.1.dist-info/RECORD
