Metadata-Version: 2.1
Name: video2sub
Version: 0.1.1
Summary: Transcribes video/audio/url to subtitles.
License: MIT
Author: MA Junyi
Author-email: mjy@z.mjyai.com
Requires-Python: >=3.8.1,<4.0.0
Classifier: License :: OSI Approved :: MIT License
Classifier: Programming Language :: Python :: 3
Classifier: Programming Language :: Python :: 3.9
Classifier: Programming Language :: Python :: 3.10
Classifier: Programming Language :: Python :: 3.11
Requires-Dist: PyYAML (>=6.0,<7.0)
Requires-Dist: nvidia-cudnn-cu11 (>=8.9.0.131,<9.0.0.0) ; sys_platform == "linux"
Requires-Dist: nvidia-nccl-cu11 (>=2.16.5,<3.0.0) ; sys_platform == "linux"
Requires-Dist: openai-whisper (>=20230314,<20230315)
Requires-Dist: yt-dlp (>=2023.3.4,<2024.0.0)
